{
    "keep": {
        "days": true,
        "amount": 14
    },
    "auditLog": "D:\\Magic Billing\\logs\\.5946c567738dbc65bc1daf0bdcbd829035647631-audit.json",
    "files": [
        {
            "date": 1748587688764,
            "name": "D:\\Magic Billing\\logs\\application-2025-05-30.log",
            "hash": "11b8f48b7dbe1a4f7a2eb664ad08777438ed857cc499343f168ab0bf9160cb2d"
        },
        {
            "date": 1748679251515,
            "name": "D:\\Magic Billing\\logs\\application-2025-05-31.log",
            "hash": "3faf1e4d5ff5c90467415f6f72ce0b00d5524dc4ed4203fb31ce044929778190"
        },
        {
            "date": 1748931901786,
            "name": "D:\\Magic Billing\\logs\\application-2025-06-03.log",
            "hash": "3472f226c59805bdb5a7796a73f87937a57e988a2dce766c94e85f6c139e5177"
        }
    ],
    "hashType": "sha256"
}